{
  "kind": "collectionType",
  "collectionName": "contact_submissions",
  "info": {
    "singularName": "contact-submission",
    "pluralName": "contact-submissions",
    "displayName": "Обращения с формы",
    "description": "Сообщения от клиентов через контактную форму"
  },
  "options": {
    "draftAndPublish": false
  },
  "pluginOptions": {},
  "attributes": {
    "name": {
      "type": "string",
      "required": true
    },
    "email": {
      "type": "email",
      "required": true
    },
    "phone": {
      "type": "string"
    },
    "message": {
      "type": "text",
      "required": true
    }
  }
}
